{
  "surahNumber": 101,
  "reciter": "Alafasy",
  "audioUrl": "https://sadekhinformatique.site/coran-audio/Coran-Arabe-Sourate-101.mp3",
  "totalDuration": 53.551,
  "verses": [
    {
      "numberInSurah": 1,
      "startTime": 0,
      "endTime": 2.351,
      "duration": 2.351
    },
    {
      "numberInSurah": 2,
      "startTime": 2.351,
      "endTime": 4.676,
      "duration": 2.325
    },
    {
      "numberInSurah": 3,
      "startTime": 4.676,
      "endTime": 10.292,
      "duration": 5.616
    },
    {
      "numberInSurah": 4,
      "startTime": 10.292,
      "endTime": 18.103,
      "duration": 7.811
    },
    {
      "numberInSurah": 5,
      "startTime": 18.103,
      "endTime": 25.731,
      "duration": 7.628
    },
    {
      "numberInSurah": 6,
      "startTime": 25.731,
      "endTime": 31.478,
      "duration": 5.747
    },
    {
      "numberInSurah": 7,
      "startTime": 31.478,
      "endTime": 35.37,
      "duration": 3.892
    },
    {
      "numberInSurah": 8,
      "startTime": 35.37,
      "endTime": 40.464,
      "duration": 5.094
    },
    {
      "numberInSurah": 9,
      "startTime": 40.464,
      "endTime": 43.964,
      "duration": 3.5
    },
    {
      "numberInSurah": 10,
      "startTime": 43.964,
      "endTime": 48.483,
      "duration": 4.519
    },
    {
      "numberInSurah": 11,
      "startTime": 48.483,
      "endTime": 53.551,
      "duration": 5.068
    }
  ]
}