{
  "surahNumber": 5,
  "reciter": "Alafasy",
  "audioUrl": "https://sadekhinformatique.site/coran-audio/Coran-Arabe-Sourate-005.mp3",
  "totalDuration": 3760.327,
  "verses": [
    {
      "numberInSurah": 1,
      "startTime": 0,
      "endTime": 30.746,
      "duration": 30.746
    },
    {
      "numberInSurah": 2,
      "startTime": 30.746,
      "endTime": 113.424,
      "duration": 82.678
    },
    {
      "numberInSurah": 3,
      "startTime": 113.424,
      "endTime": 188.003,
      "duration": 74.58
    },
    {
      "numberInSurah": 4,
      "startTime": 188.003,
      "endTime": 230.034,
      "duration": 42.031
    },
    {
      "numberInSurah": 5,
      "startTime": 230.034,
      "endTime": 293.59,
      "duration": 63.556
    },
    {
      "numberInSurah": 6,
      "startTime": 293.59,
      "endTime": 408.242,
      "duration": 114.651
    },
    {
      "numberInSurah": 7,
      "startTime": 408.242,
      "endTime": 431.229,
      "duration": 22.988
    },
    {
      "numberInSurah": 8,
      "startTime": 431.229,
      "endTime": 466.965,
      "duration": 35.736
    },
    {
      "numberInSurah": 9,
      "startTime": 466.965,
      "endTime": 479.713,
      "duration": 12.748
    },
    {
      "numberInSurah": 10,
      "startTime": 479.713,
      "endTime": 492.513,
      "duration": 12.8
    },
    {
      "numberInSurah": 11,
      "startTime": 492.513,
      "endTime": 526.002,
      "duration": 33.489
    },
    {
      "numberInSurah": 12,
      "startTime": 526.002,
      "endTime": 602.41,
      "duration": 76.408
    },
    {
      "numberInSurah": 13,
      "startTime": 602.41,
      "endTime": 641.202,
      "duration": 38.792
    },
    {
      "numberInSurah": 14,
      "startTime": 641.202,
      "endTime": 675.918,
      "duration": 34.717
    },
    {
      "numberInSurah": 15,
      "startTime": 675.918,
      "endTime": 718.655,
      "duration": 42.736
    },
    {
      "numberInSurah": 16,
      "startTime": 718.655,
      "endTime": 741.46,
      "duration": 22.805
    },
    {
      "numberInSurah": 17,
      "startTime": 741.46,
      "endTime": 783.987,
      "duration": 42.527
    },
    {
      "numberInSurah": 18,
      "startTime": 783.987,
      "endTime": 827.115,
      "duration": 43.128
    },
    {
      "numberInSurah": 19,
      "startTime": 827.115,
      "endTime": 868.545,
      "duration": 41.43
    },
    {
      "numberInSurah": 20,
      "startTime": 868.545,
      "endTime": 900.859,
      "duration": 32.313
    },
    {
      "numberInSurah": 21,
      "startTime": 900.859,
      "endTime": 920.007,
      "duration": 19.148
    },
    {
      "numberInSurah": 22,
      "startTime": 920.007,
      "endTime": 946.442,
      "duration": 26.436
    },
    {
      "numberInSurah": 23,
      "startTime": 946.442,
      "endTime": 974.028,
      "duration": 27.585
    },
    {
      "numberInSurah": 24,
      "startTime": 974.028,
      "endTime": 997.198,
      "duration": 23.171
    },
    {
      "numberInSurah": 25,
      "startTime": 997.198,
      "endTime": 1012.558,
      "duration": 15.36
    },
    {
      "numberInSurah": 26,
      "startTime": 1012.558,
      "endTime": 1030.557,
      "duration": 17.998
    },
    {
      "numberInSurah": 27,
      "startTime": 1030.557,
      "endTime": 1056.888,
      "duration": 26.331
    },
    {
      "numberInSurah": 28,
      "startTime": 1056.888,
      "endTime": 1076.846,
      "duration": 19.958
    },
    {
      "numberInSurah": 29,
      "startTime": 1076.846,
      "endTime": 1098.057,
      "duration": 21.211
    },
    {
      "numberInSurah": 30,
      "startTime": 1098.057,
      "endTime": 1108.402,
      "duration": 10.344
    },
    {
      "numberInSurah": 31,
      "startTime": 1108.402,
      "endTime": 1136.3,
      "duration": 27.899
    },
    {
      "numberInSurah": 32,
      "startTime": 1136.3,
      "endTime": 1186.926,
      "duration": 50.625
    },
    {
      "numberInSurah": 33,
      "startTime": 1186.926,
      "endTime": 1227.154,
      "duration": 40.229
    },
    {
      "numberInSurah": 34,
      "startTime": 1227.154,
      "endTime": 1244.891,
      "duration": 17.737
    },
    {
      "numberInSurah": 35,
      "startTime": 1244.891,
      "endTime": 1263.778,
      "duration": 18.887
    },
    {
      "numberInSurah": 36,
      "startTime": 1263.778,
      "endTime": 1288.359,
      "duration": 24.581
    },
    {
      "numberInSurah": 37,
      "startTime": 1288.359,
      "endTime": 1303.327,
      "duration": 14.968
    },
    {
      "numberInSurah": 38,
      "startTime": 1303.327,
      "endTime": 1322.971,
      "duration": 19.644
    },
    {
      "numberInSurah": 39,
      "startTime": 1322.971,
      "endTime": 1340.108,
      "duration": 17.136
    },
    {
      "numberInSurah": 40,
      "startTime": 1340.108,
      "endTime": 1366.805,
      "duration": 26.697
    },
    {
      "numberInSurah": 41,
      "startTime": 1366.805,
      "endTime": 1441.698,
      "duration": 74.893
    },
    {
      "numberInSurah": 42,
      "startTime": 1441.698,
      "endTime": 1473.411,
      "duration": 31.713
    },
    {
      "numberInSurah": 43,
      "startTime": 1473.411,
      "endTime": 1493.656,
      "duration": 20.245
    },
    {
      "numberInSurah": 44,
      "startTime": 1493.656,
      "endTime": 1551.177,
      "duration": 57.522
    },
    {
      "numberInSurah": 45,
      "startTime": 1551.177,
      "endTime": 1592.869,
      "duration": 41.691
    },
    {
      "numberInSurah": 46,
      "startTime": 1592.869,
      "endTime": 1627.115,
      "duration": 34.247
    },
    {
      "numberInSurah": 47,
      "startTime": 1627.115,
      "endTime": 1650.286,
      "duration": 23.171
    },
    {
      "numberInSurah": 48,
      "startTime": 1650.286,
      "endTime": 1721.417,
      "duration": 71.131
    },
    {
      "numberInSurah": 49,
      "startTime": 1721.417,
      "endTime": 1768.908,
      "duration": 47.491
    },
    {
      "numberInSurah": 50,
      "startTime": 1768.908,
      "endTime": 1784.137,
      "duration": 15.229
    },
    {
      "numberInSurah": 51,
      "startTime": 1784.137,
      "endTime": 1816.451,
      "duration": 32.313
    },
    {
      "numberInSurah": 52,
      "startTime": 1816.451,
      "endTime": 1854.798,
      "duration": 38.348
    },
    {
      "numberInSurah": 53,
      "startTime": 1854.798,
      "endTime": 1878.1,
      "duration": 23.301
    },
    {
      "numberInSurah": 54,
      "startTime": 1878.1,
      "endTime": 1939.879,
      "duration": 61.78
    },
    {
      "numberInSurah": 55,
      "startTime": 1939.879,
      "endTime": 1956.519,
      "duration": 16.64
    },
    {
      "numberInSurah": 56,
      "startTime": 1956.519,
      "endTime": 1969.842,
      "duration": 13.322
    },
    {
      "numberInSurah": 57,
      "startTime": 1969.842,
      "endTime": 2005.682,
      "duration": 35.84
    },
    {
      "numberInSurah": 58,
      "startTime": 2005.682,
      "endTime": 2021.172,
      "duration": 15.491
    },
    {
      "numberInSurah": 59,
      "startTime": 2021.172,
      "endTime": 2054.792,
      "duration": 33.62
    },
    {
      "numberInSurah": 60,
      "startTime": 2054.792,
      "endTime": 2091.128,
      "duration": 36.336
    },
    {
      "numberInSurah": 61,
      "startTime": 2091.128,
      "endTime": 2109.336,
      "duration": 18.207
    },
    {
      "numberInSurah": 62,
      "startTime": 2109.336,
      "endTime": 2124.095,
      "duration": 14.759
    },
    {
      "numberInSurah": 63,
      "startTime": 2124.095,
      "endTime": 2139.376,
      "duration": 15.282
    },
    {
      "numberInSurah": 64,
      "startTime": 2139.376,
      "endTime": 2198.439,
      "duration": 59.063
    },
    {
      "numberInSurah": 65,
      "startTime": 2198.439,
      "endTime": 2219.442,
      "duration": 21.002
    },
    {
      "numberInSurah": 66,
      "startTime": 2219.442,
      "endTime": 2252.565,
      "duration": 33.123
    },
    {
      "numberInSurah": 67,
      "startTime": 2252.565,
      "endTime": 2278.792,
      "duration": 26.227
    },
    {
      "numberInSurah": 68,
      "startTime": 2278.792,
      "endTime": 2319.36,
      "duration": 40.568
    },
    {
      "numberInSurah": 69,
      "startTime": 2319.36,
      "endTime": 2343.367,
      "duration": 24.007
    },
    {
      "numberInSurah": 70,
      "startTime": 2343.367,
      "endTime": 2372.18,
      "duration": 28.813
    },
    {
      "numberInSurah": 71,
      "startTime": 2372.18,
      "endTime": 2399.634,
      "duration": 27.455
    },
    {
      "numberInSurah": 72,
      "startTime": 2399.634,
      "endTime": 2443.703,
      "duration": 44.069
    },
    {
      "numberInSurah": 73,
      "startTime": 2443.703,
      "endTime": 2472.385,
      "duration": 28.682
    },
    {
      "numberInSurah": 74,
      "startTime": 2472.385,
      "endTime": 2483.435,
      "duration": 11.05
    },
    {
      "numberInSurah": 75,
      "startTime": 2483.435,
      "endTime": 2515.905,
      "duration": 32.47
    },
    {
      "numberInSurah": 76,
      "startTime": 2515.905,
      "endTime": 2531.239,
      "duration": 15.334
    },
    {
      "numberInSurah": 77,
      "startTime": 2531.239,
      "endTime": 2559.112,
      "duration": 27.873
    },
    {
      "numberInSurah": 78,
      "startTime": 2559.112,
      "endTime": 2578.469,
      "duration": 19.357
    },
    {
      "numberInSurah": 79,
      "startTime": 2578.469,
      "endTime": 2592.026,
      "duration": 13.558
    },
    {
      "numberInSurah": 80,
      "startTime": 2592.026,
      "endTime": 2612.245,
      "duration": 20.219
    },
    {
      "numberInSurah": 81,
      "startTime": 2612.245,
      "endTime": 2639.673,
      "duration": 27.429
    },
    {
      "numberInSurah": 82,
      "startTime": 2639.673,
      "endTime": 2677.499,
      "duration": 37.825
    },
    {
      "numberInSurah": 83,
      "startTime": 2677.499,
      "endTime": 2703.256,
      "duration": 25.757
    },
    {
      "numberInSurah": 84,
      "startTime": 2703.256,
      "endTime": 2723.657,
      "duration": 20.402
    },
    {
      "numberInSurah": 85,
      "startTime": 2723.657,
      "endTime": 2742.309,
      "duration": 18.651
    },
    {
      "numberInSurah": 86,
      "startTime": 2742.309,
      "endTime": 2755.109,
      "duration": 12.8
    },
    {
      "numberInSurah": 87,
      "startTime": 2755.109,
      "endTime": 2774.152,
      "duration": 19.043
    },
    {
      "numberInSurah": 88,
      "startTime": 2774.152,
      "endTime": 2789.878,
      "duration": 15.726
    },
    {
      "numberInSurah": 89,
      "startTime": 2789.878,
      "endTime": 2843.402,
      "duration": 53.525
    },
    {
      "numberInSurah": 90,
      "startTime": 2843.402,
      "endTime": 2870.883,
      "duration": 27.481
    },
    {
      "numberInSurah": 91,
      "startTime": 2870.883,
      "endTime": 2898.495,
      "duration": 27.611
    },
    {
      "numberInSurah": 92,
      "startTime": 2898.495,
      "endTime": 2915.997,
      "duration": 17.502
    },
    {
      "numberInSurah": 93,
      "startTime": 2915.997,
      "endTime": 2942.511,
      "duration": 26.514
    },
    {
      "numberInSurah": 94,
      "startTime": 2942.511,
      "endTime": 2976.496,
      "duration": 33.985
    },
    {
      "numberInSurah": 95,
      "startTime": 2976.496,
      "endTime": 3034.462,
      "duration": 57.966
    },
    {
      "numberInSurah": 96,
      "startTime": 3034.462,
      "endTime": 3056.457,
      "duration": 21.995
    },
    {
      "numberInSurah": 97,
      "startTime": 3056.457,
      "endTime": 3087.308,
      "duration": 30.851
    },
    {
      "numberInSurah": 98,
      "startTime": 3087.308,
      "endTime": 3099.376,
      "duration": 12.069
    },
    {
      "numberInSurah": 99,
      "startTime": 3099.376,
      "endTime": 3112.098,
      "duration": 12.722
    },
    {
      "numberInSurah": 100,
      "startTime": 3112.098,
      "endTime": 3131.115,
      "duration": 19.017
    },
    {
      "numberInSurah": 101,
      "startTime": 3131.115,
      "endTime": 3157.682,
      "duration": 26.567
    },
    {
      "numberInSurah": 102,
      "startTime": 3157.682,
      "endTime": 3168.392,
      "duration": 10.71
    },
    {
      "numberInSurah": 103,
      "startTime": 3168.392,
      "endTime": 3193.025,
      "duration": 24.633
    },
    {
      "numberInSurah": 104,
      "startTime": 3193.025,
      "endTime": 3220.454,
      "duration": 27.429
    },
    {
      "numberInSurah": 105,
      "startTime": 3220.454,
      "endTime": 3246.158,
      "duration": 25.704
    },
    {
      "numberInSurah": 106,
      "startTime": 3246.158,
      "endTime": 3315.2,
      "duration": 69.042
    },
    {
      "numberInSurah": 107,
      "startTime": 3315.2,
      "endTime": 3362.821,
      "duration": 47.621
    },
    {
      "numberInSurah": 108,
      "startTime": 3362.821,
      "endTime": 3392.784,
      "duration": 29.962
    },
    {
      "numberInSurah": 109,
      "startTime": 3392.784,
      "endTime": 3410.782,
      "duration": 17.998
    },
    {
      "numberInSurah": 110,
      "startTime": 3410.782,
      "endTime": 3486.38,
      "duration": 75.598
    },
    {
      "numberInSurah": 111,
      "startTime": 3486.38,
      "endTime": 3507.096,
      "duration": 20.715
    },
    {
      "numberInSurah": 112,
      "startTime": 3507.096,
      "endTime": 3533.113,
      "duration": 26.018
    },
    {
      "numberInSurah": 113,
      "startTime": 3533.113,
      "endTime": 3554.351,
      "duration": 21.238
    },
    {
      "numberInSurah": 114,
      "startTime": 3554.351,
      "endTime": 3588.885,
      "duration": 34.534
    },
    {
      "numberInSurah": 115,
      "startTime": 3588.885,
      "endTime": 3619.657,
      "duration": 30.772
    },
    {
      "numberInSurah": 116,
      "startTime": 3619.657,
      "endTime": 3665.345,
      "duration": 45.688
    },
    {
      "numberInSurah": 117,
      "startTime": 3665.345,
      "endTime": 3699.513,
      "duration": 34.168
    },
    {
      "numberInSurah": 118,
      "startTime": 3699.513,
      "endTime": 3715.396,
      "duration": 15.882
    },
    {
      "numberInSurah": 119,
      "startTime": 3715.396,
      "endTime": 3744.836,
      "duration": 29.44
    },
    {
      "numberInSurah": 120,
      "startTime": 3744.836,
      "endTime": 3760.327,
      "duration": 15.491
    }
  ]
}